main.py
LEGO_Block_Creator-0.4.0.dist-info/LICENSE.md
LEGO_Block_Creator-0.4.0.dist-info/METADATA
LEGO_Block_Creator-0.4.0.dist-info/WHEEL
LEGO_Block_Creator-0.4.0.dist-info/top_level.txt
LEGO_Block_Creator-0.4.0.dist-info/RECORD
