Metadata-Version: 2.1
Name: LEGO-Block-Creator
Version: 0.4.0
Summary: Offline inventory tracking of LEGO parts and sets through an easy to use CLI.
Home-page: https://github.com/Dog-Face-Development/LEGO-Block-Creator
Author: willtheorangeguy
License: # GNU GENERAL PUBLIC LICENSE
Project-URL: Homepage, https://github.com/Dog-Face-Development/LEGO-Block-Creator
Project-URL: Bug Tracker, https://github.com/Dog-Face-Development/LEGO-Block-Creator/Issues
Classifier: Development Status :: 3 - Alpha
Classifier: License :: OSI Approved :: GNU General Public License v3 (GPLv3)
Classifier: Natural Language :: English
Classifier: Operating System :: OS Independent
Classifier: Topic :: Utilities
Requires-Python: >=3.9
License-File: LICENSE.md
